LICENSE
MANIFEST.in
README.rst
setup.py
halonadm/__init__.py
halonadm/halonadm.conf
halonadm/halonadm.py
halonadm.egg-info/PKG-INFO
halonadm.egg-info/SOURCES.txt
halonadm.egg-info/dependency_links.txt
halonadm.egg-info/entry_points.txt
halonadm.egg-info/requires.txt
halonadm.egg-info/top_level.txt