Metadata-Version: 1.1
Name: halonadm
Version: 1.0.0
Summary: Manage Halon SP servers easily
Home-page: https://github.com/loxley/halonadm.git/
Author: Johan Svensson
Author-email: johan@loxley.se
License: GPLv2
Platform: UNKNOWN
Classifier: Environment :: Console
Classifier: Programming Language :: Python :: 2
Classifier: Programming Language :: Python :: 3
